outcome/peewee_validates/__init__.py
outcome/peewee_validates/peewee_validates.py
outcome/peewee_validates/py.typed
outcome_peewee_validates-2.1.2.dist-info/WHEEL
outcome_peewee_validates-2.1.2.dist-info/METADATA
outcome_peewee_validates-2.1.2.dist-info/RECORD
